PySap2000/__init__.py
PySap2000/application.py
PySap2000/config.py
PySap2000/exceptions.py
PySap2000/file.py
PySap2000/logger.py
PySap2000/analyze/__init__.py
PySap2000/analyze/analyze.py
PySap2000/analyze/data_classes.py
PySap2000/analyze/enums.py
PySap2000/area/__init__.py
PySap2000/area/auto_mesh.py
PySap2000/area/data_classes.py
PySap2000/area/edge_constraint.py
PySap2000/area/enums.py
PySap2000/area/group.py
PySap2000/area/local_axes.py
PySap2000/area/mass.py
PySap2000/area/modifier.py
PySap2000/area/offset.py
PySap2000/area/property.py
PySap2000/area/selection.py
PySap2000/area/spring.py
PySap2000/area/thickness.py
PySap2000/cable/__init__.py
PySap2000/cable/enums.py
PySap2000/cable/group.py
PySap2000/cable/mass.py
PySap2000/cable/modifier.py
PySap2000/cable/output_station.py
PySap2000/cable/property.py
PySap2000/cable/selection.py
PySap2000/constraints/__init__.py
PySap2000/constraints/constraints.py
PySap2000/constraints/enums.py
PySap2000/converters/__init__.py
PySap2000/converters/base.py
PySap2000/converters/dlubal/__init__.py
PySap2000/converters/etabs/__init__.py
PySap2000/converters/midas/__init__.py
PySap2000/database_tables/__init__.py
PySap2000/database_tables/table_keys.py
PySap2000/database_tables/tables.py
PySap2000/design/__init__.py
PySap2000/design/chinese_2010.py
PySap2000/design/data_classes.py
PySap2000/design/enums.py
PySap2000/design/steel.py
PySap2000/edit/__init__.py
PySap2000/edit/edit_area.py
PySap2000/edit/edit_frame.py
PySap2000/edit/edit_general.py
PySap2000/edit/edit_point.py
PySap2000/edit/edit_solid.py
PySap2000/edit/point_projection.py
PySap2000/export_docs/__init__.py
PySap2000/export_docs/cad_export.py
PySap2000/frame/__init__.py
PySap2000/frame/data_classes.py
PySap2000/frame/enums.py
PySap2000/frame/group.py
PySap2000/frame/hinge.py
PySap2000/frame/local_axes.py
PySap2000/frame/mass.py
PySap2000/frame/modifier.py
PySap2000/frame/property.py
PySap2000/frame/release.py
PySap2000/frame/selection.py
pysap2000-2.0.13.dist-info/LICENSE
pysap2000-2.0.13.dist-info/METADATA
pysap2000-2.0.13.dist-info/WHEEL
pysap2000-2.0.13.dist-info/top_level.txt
pysap2000-2.0.13.dist-info/RECORD
