Metadata-Version: 2.1
Name: pysap2000
Version: 2.0.13
Summary: Python wrapper for SAP2000 structural analysis software API with LangChain AI agent support
Home-page: https://github.com/jiangyao/pysap2000
Author: jiangyao
Author-email: 631488424@qq.com
License: MIT
Platform: UNKNOWN
Classifier: Development Status :: 4 - Beta
Classifier: License :: OSI Approved :: MIT License
Classifier: Operating System :: Microsoft :: Windows
Classifier: Programming Language :: Python :: 3
Requires-Python: >=3.8
License-File: LICENSE
Requires-Dist: comtypes (>=1.1.0)
